tap_googlemeet/__init__.py
tap_googlemeet/client.py
tap_googlemeet/schemas/call_ended.json
tap_googlemeet/secrets_manager.py
tap_googlemeet/streams.py
tap_googlemeet/tap.py
tap_googlemeet-0.0.2.dist-info/LICENSE
tap_googlemeet-0.0.2.dist-info/METADATA
tap_googlemeet-0.0.2.dist-info/WHEEL
tap_googlemeet-0.0.2.dist-info/entry_points.txt
tap_googlemeet-0.0.2.dist-info/RECORD
