Metadata-Version: 2.1
Name: tap-googlemeet
Version: 0.0.2
Summary: `tap-googlemeet` is a Singer tap for GoogleMeet, built with the Meltano Singer SDK.
License: Apache-2.0
Keywords: ELT,GoogleMeet
Author: Hidde Stokvis
Requires-Python: >=3.7.1,<3.12
Classifier: License :: OSI Approved :: Apache Software License
Classifier: Programming Language :: Python :: 3
Classifier: Programming Language :: Python :: 3.8
Classifier: Programming Language :: Python :: 3.9
Classifier: Programming Language :: Python :: 3.10
Classifier: Programming Language :: Python :: 3.11
Provides-Extra: s3
Requires-Dist: boto3 (>=1.28.3,<2.0.0)
Requires-Dist: fs-s3fs (>=1.1.1,<2.0.0) ; extra == "s3"
Requires-Dist: google-api-python-client (>=2.93.0,<3.0.0)
Requires-Dist: google-auth-httplib2 (>=0.1.0,<0.2.0)
Requires-Dist: google-auth-oauthlib (>=1.0.0,<2.0.0)
Requires-Dist: iso8601 (>=2.0.0,<3.0.0)
Requires-Dist: requests (>=2.31.0,<3.0.0)
Requires-Dist: singer-sdk (>=0.30.0,<0.31.0)
